LICENSE
MANIFEST.in
README.rst
requirements.txt
setup.py
bin/drasticali
drasticali/__init__.py
drasticali/drasticali-add.ipynb
drasticali/drasticali-edit.ipynb
drasticali/drasticali-inspect.ipynb
drasticali/drasticali-run.ipynb
drasticali/drasticali.py
drasticali.egg-info/PKG-INFO
drasticali.egg-info/SOURCES.txt
drasticali.egg-info/dependency_links.txt
drasticali.egg-info/requires.txt
drasticali.egg-info/top_level.txt
recipes/extended_recipe.json
recipes/hdr_recipe.json
recipes/noise_recipe.json
recipes/point_recipe.json
recipes/input/extended_skymodel.txt
recipes/input/hdr_skymodel.txt
recipes/input/point_skymodel.txt