Metadata-Version: 1.1
Name: drasticali
Version: 0.0.9.2
Summary: Diverse Radio Astronomy Software Tools for Imaging and Calibration
Home-page: https://github.com/Athanaseus/drasticali
Author: Athanaseus Ramaila
Author-email: aramaila@ska.ac.za
License: GNU GPL 3
Platform: OS Independent
Classifier: Intended Audience :: Developers
Classifier: Programming Language :: Python :: 3
Classifier: Topic :: Scientific/Engineering :: Astronomy
Classifier: Topic :: Software Development :: Libraries :: Python Modules
